{"data":{"site":{"siteMetadata":{"author":"Song Wang","homeCity":"Beijing"}},"markdownRemark":{"html":"<div class=\"gatsby-highlight\" data-language=\"js\"><pre class=\"language-js\"><code class=\"language-js\"><span class=\"token keyword\">const</span> <span class=\"token function-variable function\">constructTwoD</span> <span class=\"token operator\">=</span> <span class=\"token punctuation\">(</span> columnNumber<span class=\"token punctuation\">,</span> rowNumber <span class=\"token punctuation\">)</span> <span class=\"token operator\">=></span> <span class=\"token punctuation\">[</span><span class=\"token operator\">...</span><span class=\"token function\">Array</span><span class=\"token punctuation\">(</span>rowNumber<span class=\"token punctuation\">)</span><span class=\"token punctuation\">]</span><span class=\"token punctuation\">.</span><span class=\"token function\">map</span><span class=\"token punctuation\">(</span>row<span class=\"token operator\">=></span><span class=\"token function\">Array</span><span class=\"token punctuation\">(</span>columnNumber<span class=\"token punctuation\">)</span><span class=\"token punctuation\">)</span>\n\n<span class=\"token function\">constructTwoD</span><span class=\"token punctuation\">(</span><span class=\"token number\">2</span><span class=\"token punctuation\">,</span><span class=\"token number\">3</span><span class=\"token punctuation\">)</span>\n<span class=\"token comment\">// => [[ , , ], [ , , ]]</span></code></pre></div>","excerpt":"","fields":{"slug":"/blog/2017-08-04-creating-2d-array-the-es6-way/","tagSlugs":["/tags/javascript/"]},"frontmatter":{"title":"Creating 2d Array the ES6 way","tags":["javascript"],"description":null,"date":"August 04, 2017"}}},"pageContext":{"slug":"/blog/2017-08-04-creating-2d-array-the-es6-way/","previous":{"fields":{"slug":"/blog/2017-08-03-dont-use-arrow-function-for-closure/"},"frontmatter":{"title":"Don't use arrow function for closure","tags":["javascript"]}},"next":{"fields":{"slug":"/blog/2017-08-04-be-careful-call-backing-arrayfill/"},"frontmatter":{"title":"Be careful call backing array.fill()","tags":["javascript"]}}}}