{"data":{"site":{"siteMetadata":{"author":"Song Wang","homeCity":"Beijing"}},"markdownRemark":{"html":"<p>lol</p>","excerpt":"lol","fields":{"slug":"/blog/2017-08-21-array-in-javascript-is-object/","tagSlugs":["/tags/javascript/"]},"frontmatter":{"title":"Array in javascript is object","tags":["javascript"],"description":null,"date":"August 21, 2017"}}},"pageContext":{"slug":"/blog/2017-08-21-array-in-javascript-is-object/","previous":{"fields":{"slug":"/blog/2017-08-18-enlarge-indentation-in-functional-programming/"},"frontmatter":{"title":"Enlarge indentation in functional programming","tags":["coding","functional programming"]}},"next":{"fields":{"slug":"/blog/2017-08-29-spread-operator-doubles-runtime/"},"frontmatter":{"title":"Spread operator doubles runtime","tags":["javascript"]}}}}